odoo/addons/sale_transaction_form_link/README.rst
odoo/addons/sale_transaction_form_link/__init__.py
odoo/addons/sale_transaction_form_link/__manifest__.py
odoo/addons/sale_transaction_form_link/demo/payment_transaction.xml
odoo/addons/sale_transaction_form_link/i18n/es.po
odoo/addons/sale_transaction_form_link/i18n/it.po
odoo/addons/sale_transaction_form_link/i18n/sale_transaction_form_link.pot
odoo/addons/sale_transaction_form_link/models/__init__.py
odoo/addons/sale_transaction_form_link/models/sale_order.py
odoo/addons/sale_transaction_form_link/readme/CONTRIBUTORS.md
odoo/addons/sale_transaction_form_link/readme/DESCRIPTION.md
odoo/addons/sale_transaction_form_link/readme/USAGE.md
odoo/addons/sale_transaction_form_link/static/description/icon.png
odoo/addons/sale_transaction_form_link/static/description/index.html
odoo/addons/sale_transaction_form_link/tests/__init__.py
odoo/addons/sale_transaction_form_link/tests/test_sale_order.py
odoo/addons/sale_transaction_form_link/views/sale_order.xml
odoo_addon_sale_transaction_form_link-18.0.1.0.0.2.dist-info/METADATA
odoo_addon_sale_transaction_form_link-18.0.1.0.0.2.dist-info/WHEEL
odoo_addon_sale_transaction_form_link-18.0.1.0.0.2.dist-info/top_level.txt
odoo_addon_sale_transaction_form_link-18.0.1.0.0.2.dist-info/RECORD
